MANIFEST.in
README.md
pyproject.toml
requirements.txt
setup.py
ai_image_platform/__init__.py
ai_image_platform.egg-info/PKG-INFO
ai_image_platform.egg-info/SOURCES.txt
ai_image_platform.egg-info/dependency_links.txt
ai_image_platform.egg-info/entry_points.txt
ai_image_platform.egg-info/requires.txt
ai_image_platform.egg-info/top_level.txt
ai_image_platform/api/__init__.py
ai_image_platform/api/flask_app.py
ai_image_platform/core/__init__.py
ai_image_platform/core/gemini_chat.py
ai_image_platform/core/image_analysis.py
ai_image_platform/core/image_editing.py
ai_image_platform/core/image_generation.py
ai_image_platform/core/pollinations_client.py
ai_image_platform/static/__init__.py
ai_image_platform/templates/__init__.py
ai_image_platform/templates/docs.html
ai_image_platform/templates/index.html