Metadata-Version: 2.4
Name: ai-image-platform
Version: 1.0.0
Summary: Comprehensive Python library for AI-powered image processing and multimodal chat
Home-page: https://github.com/your-username/ai-image-platform
Author: AI Image Platform Team
Author-email: contact@ai-image-platform.dev
Project-URL: Documentation, https://your-domain.com/docs
Project-URL: Source, https://github.com/your-username/ai-image-platform
Project-URL: Bug Reports, https://github.com/your-username/ai-image-platform/issues
Keywords: ai,artificial intelligence,image processing,image generation,image analysis,computer vision,gemini ai,multimodal chat,flask api,serverless,pollinations,text-to-image
Classifier: Development Status :: 4 - Beta
Classifier: Intended Audience :: Developers
Classifier: Topic :: Software Development :: Libraries :: Python Modules
Classifier: Topic :: Scientific/Engineering :: Artificial Intelligence
Classifier: Topic :: Multimedia :: Graphics
Classifier: License :: OSI Approved :: MIT License
Classifier: Programming Language :: Python :: 3
Classifier: Programming Language :: Python :: 3.8
Classifier: Programming Language :: Python :: 3.9
Classifier: Programming Language :: Python :: 3.10
Classifier: Programming Language :: Python :: 3.11
Classifier: Programming Language :: Python :: 3.12
Classifier: Framework :: Flask
Classifier: Environment :: Web Environment
Classifier: Operating System :: OS Independent
Requires-Python: >=3.8
Requires-Dist: Flask
Requires-Dist: Pillow
Requires-Dist: APScheduler
Requires-Dist: apscheduler
Requires-Dist: flask
Requires-Dist: gunicorn
Requires-Dist: numpy
Requires-Dist: pillow
Requires-Dist: requests
Requires-Dist: sift-stack-py
Requires-Dist: werkzeug
Requires-Dist: google-generativeai
Requires-Dist: google-genai
Requires-Dist: build
Requires-Dist: twine
Provides-Extra: dev
Requires-Dist: pytest>=7.0.0; extra == "dev"
Requires-Dist: pytest-cov>=4.0.0; extra == "dev"
Requires-Dist: black>=23.0.0; extra == "dev"
Requires-Dist: flake8>=6.0.0; extra == "dev"
Requires-Dist: mypy>=1.0.0; extra == "dev"
Provides-Extra: docs
Requires-Dist: sphinx>=6.0.0; extra == "docs"
Requires-Dist: sphinx-rtd-theme>=1.2.0; extra == "docs"
Dynamic: author
Dynamic: author-email
Dynamic: classifier
Dynamic: description
Dynamic: description-content-type
Dynamic: home-page
Dynamic: keywords
Dynamic: project-url
Dynamic: provides-extra
Dynamic: requires-dist
Dynamic: requires-python
Dynamic: summary
